pybbt/__init__.py
pybbt/__main__.py
pybbt/assertion.py
pybbt/case.py
pybbt/context.py
pybbt/error_case.py
pybbt/launcher.py
pybbt/logger.py
pybbt/safe_thread.py
pybbt/subcase.py
pybbt/pybbt/__init__.py
pybbt/pybbt/__main__.py
pybbt/pybbt/assertion.py
pybbt/pybbt/case.py
pybbt/pybbt/context.py
pybbt/pybbt/error_case.py
pybbt/pybbt/launcher.py
pybbt/pybbt/logger.py
pybbt/pybbt/safe_thread.py
pybbt/pybbt/subcase.py
pybbt/pybbt/utils/__init__.py
pybbt/pybbt/utils/filesystem.py
pybbt/pybbt/utils/timer.py
pybbt/utils/__init__.py
pybbt/utils/filesystem.py
pybbt/utils/timer.py
pybbt-1.0.1.dist-info/METADATA
pybbt-1.0.1.dist-info/WHEEL
pybbt-1.0.1.dist-info/entry_points.txt
pybbt-1.0.1.dist-info/licenses/LICENSE
pybbt-1.0.1.dist-info/RECORD
