Metadata-Version: 2.1
Name: pybbt
Version: 1.0.1
Summary: pybbt is a Python-based tool that simplifies black box testing of software. It provides a range of auxiliary functions and the ability to filter test cases, making your testing process more efficient and manageable.
Project-URL: Homepage, https://github.com/tair-opensource/pybbt
Project-URL: Bug Tracker, https://github.com/tair-opensource/pybbt/issues
Author-email: Tair <tair-opensource@alibabacloud.com>, suxb201 <suxb201@gmail.com>
License-File: LICENSE
Classifier: License :: OSI Approved :: MIT License
Classifier: Operating System :: OS Independent
Classifier: Programming Language :: Python :: 3
Requires-Python: >=3.9
Requires-Dist: rich>=13.5.2
